{
  "ogmoVersion": "3.3.0",
  "width": 184,
  "height": 152,
  "offsetX": 0,
  "offsetY": 0,
  "values": {"auto_scroll": false},
  "layers": [
    {
      "name": "foreground_tiles",
      "_eid": "40208349",
      "offsetX": 0,
      "offsetY": 0,
      "gridCellWidth": 8,
      "gridCellHeight": 8,
      "gridCellsX": 23,
      "gridCellsY": 19,
      "tileset": "tiles",
      "data": [-1, -1, -1, -1, -1, -1, -1, -1, -1, -1, -1, -1, -1, -1, -1, -1, -1, -1, -1, -1, -1, -1, -1, -1, -1, -1, -1, -1, -1, -1, -1, -1, -1, -1, -1, -1, -1, -1, -1, -1, -1, -1, -1, -1, -1, -1, -1, -1, -1, -1, -1, -1, -1, -1, -1, -1, -1, -1, -1, -1, -1, -1, -1, -1, -1, -1, -1, -1, -1, -1, -1, -1, -1, -1, -1, -1, -1, -1, -1, -1, -1, -1, -1, -1, -1, -1, -1, -1, -1, -1, -1, -1, -1, -1, -1, -1, -1, -1, -1, -1, -1, -1, -1, -1, -1, -1, -1, -1, -1, -1, -1, -1, -1, -1, -1, -1, -1, -1, -1, -1, -1, -1, -1, -1, -1, -1, -1, -1, -1, -1, -1, -1, -1, -1, -1, -1, -1, -1, -1, -1, -1, -1, -1, -1, -1, -1, -1, -1, -1, -1, -1, -1, -1, -1, -1, -1, -1, -1, -1, -1, -1, -1, -1, -1, -1, -1, -1, -1, -1, -1, -1, -1, -1, -1, -1, -1, -1, -1, -1, -1, -1, -1, -1, -1, -1, -1, -1, -1, -1, -1, -1, -1, -1, -1, -1, -1, -1, -1, -1, -1, -1, -1, -1, -1, -1, -1, -1, -1, -1, -1, -1, -1, -1, -1, -1, -1, -1, -1, -1, -1, -1, -1, -1, -1, -1, -1, -1, -1, -1, -1, -1, -1, -1, -1, -1, -1, -1, -1, -1, -1, -1, -1, -1, -1, -1, -1, -1, -1, -1, -1, -1, -1, -1, -1, -1, -1, -1, -1, -1, -1, -1, -1, -1, -1, -1, -1, -1, -1, -1, -1, -1, -1, -1, -1, -1, -1, -1, -1, -1, -1, -1, -1, -1, -1, -1, -1, -1, -1, -1, -1, -1, -1, -1, -1, -1, -1, -1, -1, -1, -1, -1, -1, -1, -1, -1, -1, -1, -1, -1, -1, -1, -1, -1, -1, -1, -1, -1, -1, -1, -1, -1, -1, -1, -1, -1, -1, -1, -1, -1, -1, -1, -1, -1, -1, -1, -1, -1, -1, -1, -1, -1, -1, -1, -1, -1, -1, -1, -1, -1, -1, -1, -1, -1, -1, -1, -1, -1, -1, -1, -1, -1, -1, -1, -1, -1, -1, -1, -1, -1, -1, -1, -1, -1, -1, -1, -1, -1, -1, -1, -1, -1, -1, -1, -1, -1, -1, -1, -1, -1, -1, -1, -1, -1, -1, -1, -1, -1, -1, -1, -1, -1, -1, -1, -1, -1, -1, -1, -1, -1, -1, -1, -1, -1, -1, -1, -1, -1, -1, -1, -1, -1, -1, -1, -1, -1, -1, -1, -1, -1, -1, -1, -1, -1, -1, -1, -1, -1],
      "exportMode": 0,
      "arrayMode": 0
    },
    {
      "name": "entities",
      "_eid": "26479297",
      "offsetX": 0,
      "offsetY": 0,
      "gridCellWidth": 8,
      "gridCellHeight": 8,
      "gridCellsX": 23,
      "gridCellsY": 19,
      "entities": [
        {"name": "player", "id": 0, "_eid": "26473891", "x": 0, "y": 136, "originX": 0, "originY": 0},
        {
          "name": "anomaly",
          "id": 1,
          "_eid": "30850794",
          "x": 16,
          "y": 136,
          "originX": 0,
          "originY": 0,
          "values": {"vertical": true, "initial_direction": -1}
        },
        {
          "name": "anomaly",
          "id": 2,
          "_eid": "30850794",
          "x": 24,
          "y": 128,
          "originX": 0,
          "originY": 0,
          "values": {"vertical": true, "initial_direction": -1}
        },
        {
          "name": "anomaly",
          "id": 4,
          "_eid": "30850794",
          "x": 48,
          "y": 136,
          "originX": 0,
          "originY": 0,
          "values": {"vertical": true, "initial_direction": -1}
        },
        {
          "name": "anomaly",
          "id": 5,
          "_eid": "30850794",
          "x": 56,
          "y": 128,
          "originX": 0,
          "originY": 0,
          "values": {"vertical": true, "initial_direction": -1}
        },
        {
          "name": "anomaly",
          "id": 8,
          "_eid": "30850794",
          "x": 24,
          "y": 96,
          "originX": 0,
          "originY": 0,
          "values": {"vertical": true, "initial_direction": 1}
        },
        {
          "name": "anomaly",
          "id": 10,
          "_eid": "30850794",
          "x": 48,
          "y": 88,
          "originX": 0,
          "originY": 0,
          "values": {"vertical": true, "initial_direction": 1}
        },
        {
          "name": "anomaly",
          "id": 11,
          "_eid": "30850794",
          "x": 56,
          "y": 96,
          "originX": 0,
          "originY": 0,
          "values": {"vertical": true, "initial_direction": 1}
        },
        {"name": "hazard_bounce_marker", "id": 13, "_eid": "31169632", "x": 16, "y": 112, "originX": 0, "originY": 0},
        {"name": "hazard_bounce_marker", "id": 14, "_eid": "31169632", "x": 24, "y": 112, "originX": 0, "originY": 0},
        {"name": "hazard_bounce_marker", "id": 16, "_eid": "31169632", "x": 48, "y": 112, "originX": 0, "originY": 0},
        {"name": "hazard_bounce_marker", "id": 17, "_eid": "31169632", "x": 56, "y": 112, "originX": 0, "originY": 0},
        {
          "name": "anomaly",
          "id": 24,
          "_eid": "30850794",
          "x": 128,
          "y": 120,
          "originX": 0,
          "originY": 0,
          "values": {"vertical": false, "initial_direction": -1}
        },
        {"name": "hazard_bounce_marker", "id": 25, "_eid": "31169632", "x": 80, "y": 120, "originX": 0, "originY": 0},
        {
          "name": "anomaly",
          "id": 28,
          "_eid": "30850794",
          "x": 16,
          "y": 88,
          "originX": 0,
          "originY": 0,
          "values": {"vertical": true, "initial_direction": 1}
        },
        {
          "name": "anomaly",
          "id": 29,
          "_eid": "30850794",
          "x": 72,
          "y": 64,
          "originX": 0,
          "originY": 0,
          "values": {"vertical": false, "initial_direction": -1}
        },
        {
          "name": "anomaly",
          "id": 30,
          "_eid": "30850794",
          "x": 56,
          "y": 64,
          "originX": 0,
          "originY": 0,
          "values": {"vertical": false, "initial_direction": -1}
        },
        {
          "name": "anomaly",
          "id": 31,
          "_eid": "30850794",
          "x": 40,
          "y": 64,
          "originX": 0,
          "originY": 0,
          "values": {"vertical": false, "initial_direction": -1}
        },
        {
          "name": "anomaly",
          "id": 32,
          "_eid": "30850794",
          "x": 24,
          "y": 64,
          "originX": 0,
          "originY": 0,
          "values": {"vertical": false, "initial_direction": -1}
        },
        {
          "name": "anomaly",
          "id": 33,
          "_eid": "30850794",
          "x": 8,
          "y": 64,
          "originX": 0,
          "originY": 0,
          "values": {"vertical": false, "initial_direction": -1}
        },
        {"name": "hazard_bounce_marker", "id": 34, "_eid": "31169632", "x": 0, "y": 64, "originX": 0, "originY": 0},
        {
          "name": "anomaly",
          "id": 35,
          "_eid": "30850794",
          "x": 168,
          "y": 72,
          "originX": 0,
          "originY": 0,
          "values": {"vertical": false, "initial_direction": -1}
        }
      ]
    },
    {
      "name": "collectibles",
      "_eid": "32723121",
      "offsetX": 0,
      "offsetY": 0,
      "gridCellWidth": 8,
      "gridCellHeight": 8,
      "gridCellsX": 23,
      "gridCellsY": 19,
      "entities": [
        {"name": "coin", "id": 0, "_eid": "26570596", "x": 16, "y": 112, "originX": 0, "originY": 0},
        {"name": "coin", "id": 1, "_eid": "26570596", "x": 24, "y": 112, "originX": 0, "originY": 0},
        {"name": "coin", "id": 2, "_eid": "26570596", "x": 48, "y": 112, "originX": 0, "originY": 0},
        {"name": "coin", "id": 3, "_eid": "26570596", "x": 56, "y": 112, "originX": 0, "originY": 0},
        {"name": "coin", "id": 4, "_eid": "26570596", "x": 144, "y": 88, "originX": 0, "originY": 0},
        {"name": "coin", "id": 5, "_eid": "26570596", "x": 152, "y": 88, "originX": 0, "originY": 0},
        {"name": "coin", "id": 6, "_eid": "26570596", "x": 168, "y": 88, "originX": 0, "originY": 0},
        {"name": "coin", "id": 7, "_eid": "26570596", "x": 160, "y": 88, "originX": 0, "originY": 0},
        {"name": "coin", "id": 8, "_eid": "26570596", "x": 136, "y": 88, "originX": 0, "originY": 0},
        {"name": "coin", "id": 9, "_eid": "26570596", "x": 136, "y": 96, "originX": 0, "originY": 0},
        {"name": "coin", "id": 10, "_eid": "26570596", "x": 96, "y": 16, "originX": 0, "originY": 0},
        {"name": "coin", "id": 11, "_eid": "26570596", "x": 72, "y": 16, "originX": 0, "originY": 0},
        {"name": "coin", "id": 12, "_eid": "26570596", "x": 120, "y": 16, "originX": 0, "originY": 0},
        {"name": "coin", "id": 13, "_eid": "26570596", "x": 144, "y": 16, "originX": 0, "originY": 0},
        {"name": "coin", "id": 14, "_eid": "26570596", "x": 168, "y": 16, "originX": 0, "originY": 0},
        {"name": "coin", "id": 15, "_eid": "26570596", "x": 48, "y": 16, "originX": 0, "originY": 0},
        {"name": "coin", "id": 16, "_eid": "26570596", "x": 0, "y": 32, "originX": 0, "originY": 0},
        {"name": "coin", "id": 17, "_eid": "26570596", "x": 16, "y": 40, "originX": 0, "originY": 0},
        {"name": "coin", "id": 18, "_eid": "26570596", "x": 40, "y": 40, "originX": 0, "originY": 0},
        {"name": "coin", "id": 19, "_eid": "26570596", "x": 64, "y": 40, "originX": 0, "originY": 0},
        {"name": "coin", "id": 20, "_eid": "26570596", "x": 16, "y": 16, "originX": 0, "originY": 0},
        {"name": "coin", "id": 21, "_eid": "26570596", "x": 144, "y": 80, "originX": 0, "originY": 0},
        {"name": "coin", "id": 22, "_eid": "26570596", "x": 168, "y": 80, "originX": 0, "originY": 0},
        {"name": "coin", "id": 23, "_eid": "26570596", "x": 152, "y": 72, "originX": 0, "originY": 0},
        {"name": "coin", "id": 24, "_eid": "26570596", "x": 160, "y": 72, "originX": 0, "originY": 0},
        {"name": "coin", "id": 25, "_eid": "26570596", "x": 168, "y": 72, "originX": 0, "originY": 0},
        {"name": "coin", "id": 26, "_eid": "26570596", "x": 160, "y": 72, "originX": 0, "originY": 0},
        {"name": "coin", "id": 27, "_eid": "26570596", "x": 136, "y": 72, "originX": 0, "originY": 0},
        {"name": "coin", "id": 30, "_eid": "26570596", "x": 144, "y": 72, "originX": 0, "originY": 0},
        {"name": "coin", "id": 31, "_eid": "26570596", "x": 112, "y": 72, "originX": 0, "originY": 0},
        {"name": "coin", "id": 32, "_eid": "26570596", "x": 120, "y": 72, "originX": 0, "originY": 0},
        {"name": "coin", "id": 33, "_eid": "26570596", "x": 128, "y": 72, "originX": 0, "originY": 0},
        {"name": "coin", "id": 34, "_eid": "26570596", "x": 120, "y": 72, "originX": 0, "originY": 0},
        {"name": "coin", "id": 35, "_eid": "26570596", "x": 96, "y": 72, "originX": 0, "originY": 0},
        {"name": "coin", "id": 36, "_eid": "26570596", "x": 104, "y": 72, "originX": 0, "originY": 0},
        {"name": "coin", "id": 37, "_eid": "26570596", "x": 88, "y": 64, "originX": 0, "originY": 0},
        {"name": "coin", "id": 38, "_eid": "26570596", "x": 88, "y": 72, "originX": 0, "originY": 0}
      ]
    },
    {
      "name": "walls",
      "_eid": "26473805",
      "offsetX": 0,
      "offsetY": 0,
      "gridCellWidth": 8,
      "gridCellHeight": 8,
      "gridCellsX": 23,
      "gridCellsY": 19,
      "tileset": "tiles",
      "data": [-1, -1, -1, -1, -1, -1, -1, -1, -1, -1, -1, -1, -1, -1, -1, -1, -1, -1, -1, -1, -1, -1, -1, -1, -1, -1, -1, -1, -1, -1, -1, -1, -1, -1, -1, -1, -1, -1, -1, -1, -1, -1, -1, -1, -1, -1, -1, -1, -1, -1, -1, 1, -1, -1, 1, -1, -1, 1, -1, -1, 1, -1, -1, 1, -1, -1, 1, -1, 5, -1, -1, 1, -1, -1, -1, -1, -1, -1, -1, -1, -1, -1, -1, -1, -1, -1, -1, -1, -1, -1, -1, 7, -1, -1, -1, -1, -1, -1, -1, -1, -1, -1, -1, -1, -1, -1, -1, -1, -1, -1, -1, -1, -1, -1, 7, 1, -1, -1, -1, -1, -1, -1, -1, -1, -1, -1, -1, -1, -1, -1, -1, -1, -1, -1, -1, -1, -1, 7, -1, -1, 1, -1, -1, 1, -1, -1, 1, -1, -1, -1, -1, -1, -1, -1, -1, -1, -1, -1, -1, -1, 7, -1, -1, -1, -1, -1, -1, -1, -1, -1, -1, -1, -1, -1, -1, -1, -1, -1, -1, -1, -1, -1, -1, 7, -1, -1, -1, -1, -1, -1, -1, -1, -1, -1, 1, -1, 1, 1, 1, 1, 1, 1, 1, 1, 1, 1, 1, 2, 2, 2, 2, 2, 2, 2, 2, 2, 2, 1, -1, -1, -1, -1, -1, -1, -1, -1, -1, -1, -1, 1, 11, 11, 11, 11, 11, 11, 11, 11, 11, 11, 1, 1, 1, 1, 1, 1, 1, 1, -1, 1, 1, -1, 1, -1, -1, -1, -1, -1, -1, -1, -1, -1, -1, 1, 1, 1, 1, 1, 1, 1, -1, -1, -1, -1, -1, 1, -1, -1, -1, -1, -1, -1, -1, -1, -1, -1, 1, 1, 1, 1, 1, 1, 1, -1, 1, 1, 1, 1, 1, -1, -1, -1, -1, -1, -1, -1, -1, -1, -1, 1, 1, 1, 1, -1, -1, -1, -1, -1, -1, -1, 1, 1, -1, -1, -1, -1, -1, -1, -1, -1, -1, -1, 1, 1, 1, 1, -1, 1, 1, 1, 1, 1, -1, 1, 1, -1, -1, -1, -1, -1, -1, -1, -1, -1, -1, -1, -1, -1, -1, -1, -1, -1, -1, -1, -1, -1, -1, 1, -1, -1, -1, -1, -1, -1, -1, -1, -1, -1, 1, -1, 1, 1, 1, 1, 1, -1, 1, 1, 1, 1, 1, -1, -1, -1, -1, -1, -1, -1, -1, -1, 1, 1, 1, 1, 1, 1, 1, 1, 1, 1, 1, 1, 1, 1, 1, 1, 1, 1, 1, 1, 1, 1, 1, 1, 1, 1, 1, 1, 1, 1, 1, 1, 1, 1, 1, 1, 1],
      "exportMode": 0,
      "arrayMode": 0
    },
    {
      "name": "background_tiles",
      "_eid": "40209875",
      "offsetX": 0,
      "offsetY": 0,
      "gridCellWidth": 8,
      "gridCellHeight": 8,
      "gridCellsX": 23,
      "gridCellsY": 19,
      "tileset": "tiles",
      "data": [-1, -1, -1, -1, -1, -1, -1, -1, -1, -1, -1, -1, -1, -1, -1, -1, -1, -1, -1, -1, -1, -1, -1, -1, -1, -1, -1, -1, -1, -1, -1, -1, -1, -1, -1, -1, -1, -1, -1, -1, -1, -1, -1, -1, -1, -1, -1, -1, -1, -1, -1, -1, -1, -1, -1, -1, -1, -1, -1, -1, -1, -1, -1, -1, -1, -1, -1, -1, -1, -1, -1, -1, -1, -1, -1, -1, -1, -1, -1, -1, -1, -1, -1, -1, -1, -1, -1, -1, -1, -1, -1, -1, -1, -1, -1, -1, -1, -1, -1, -1, -1, -1, -1, -1, -1, -1, -1, -1, -1, -1, -1, -1, -1, -1, -1, -1, -1, -1, -1, -1, -1, -1, -1, -1, -1, -1, -1, -1, -1, -1, -1, -1, -1, -1, -1, -1, -1, -1, -1, -1, -1, -1, -1, -1, -1, -1, -1, -1, -1, -1, -1, -1, -1, -1, -1, -1, -1, -1, -1, -1, -1, -1, -1, -1, -1, -1, -1, -1, -1, -1, -1, -1, -1, -1, -1, -1, -1, -1, -1, -1, -1, -1, -1, -1, -1, -1, -1, -1, -1, -1, -1, -1, -1, -1, -1, -1, -1, -1, -1, -1, -1, -1, -1, -1, -1, -1, -1, -1, -1, -1, -1, -1, -1, -1, -1, -1, -1, -1, -1, -1, -1, -1, -1, -1, -1, -1, -1, -1, -1, -1, -1, -1, -1, -1, -1, -1, -1, -1, -1, -1, -1, -1, -1, -1, -1, -1, -1, -1, -1, -1, -1, -1, -1, -1, -1, -1, -1, -1, -1, -1, -1, -1, -1, -1, -1, -1, -1, -1, -1, -1, -1, -1, -1, -1, -1, -1, -1, -1, -1, -1, -1, -1, -1, -1, -1, -1, -1, -1, -1, -1, -1, -1, -1, -1, -1, -1, -1, -1, -1, -1, -1, -1, -1, -1, -1, -1, -1, -1, -1, -1, -1, -1, -1, -1, -1, -1, -1, -1, -1, -1, -1, -1, -1, -1, -1, -1, -1, -1, -1, -1, -1, -1, -1, -1, -1, -1, -1, -1, -1, -1, -1, -1, -1, -1, -1, -1, -1, -1, -1, -1, -1, -1, -1, -1, -1, -1, -1, -1, -1, -1, -1, -1, -1, -1, -1, -1, -1, -1, -1, -1, -1, -1, -1, -1, -1, -1, -1, -1, -1, -1, -1, -1, -1, -1, -1, -1, -1, -1, -1, -1, -1, -1, -1, -1, -1, -1, -1, -1, -1, -1, -1, -1, -1, -1, -1, -1, -1, -1, -1, -1, -1, -1, -1, -1, -1, -1, -1, -1, -1, -1, -1, -1, -1, -1, -1, -1, -1, -1, -1, -1, -1, -1, -1, -1, -1, -1, -1],
      "exportMode": 0,
      "arrayMode": 0
    }
  ]
}